hula/ComprehensiveNet.py
hula/DeepR.py
hula/MemoryF.py
hula/RecursiveL.py
hula/ReinforcementL.py
hula/__init__ .py
hula/rlutils.py
hula-0.1.0.0.dist-info/METADATA
hula-0.1.0.0.dist-info/WHEEL
hula-0.1.0.0.dist-info/top_level.txt
hula-0.1.0.0.dist-info/RECORD
