Metadata-Version: 2.1
Name: hula
Version: 0.1.0.0
Summary: Experimental learning methods. The first appearance of these methods.
Home-page: https://robert-bassett-coder.gitbook.io/workspace/
Author: Robert Bassett
Author-email: robert.bassett.coder@gmail.com
License: UNKNOWN
Platform: UNKNOWN
Classifier: Programming Language :: Python :: 3
Classifier: License :: OSI Approved :: GNU General Public License (GPL)
Classifier: Operating System :: OS Independent
Requires-Dist: numpy
